{
  "1": [
    2,
    4
  ],
  "2": [
    7,
    14
  ],
  "3": [
    7,
    4
  ],
  "4": [
    2,
    12
  ],
  "5": [
    7,
    4
  ],
  "6": [
    7,
    10
  ],
  "7": [
    2,
    7
  ],
  "8": [
    14,
    1
  ],
  "9": [
    2,
    10
  ],
  "10": [
    2,
    14
  ],
  "11": [
    7,
    0
  ],
  "12": [
    0,
    7
  ],
  "13": [
    0,
    3
  ],
  "14": [
    2,
    12
  ],
  "15": [
    2,
    13
  ],
  "16": [
    7,
    10
  ],
  "17": [
    7,
    3
  ],
  "18": [
    4,
    0
  ],
  "19": [
    7,
    12
  ],
  "20": [
    2,
    12
  ],
  "21": [
    7,
    4
  ],
  "22": [
    7,
    12
  ],
  "23": [
    7,
    12
  ],
  "24": [
    2,
    12
  ],
  "25": [
    7,
    0
  ],
  "26": [
    2,
    10
  ],
  "27": [
    7,
    10
  ],
  "28": [
    2,
    4
  ],
  "29": [
    7,
    4
  ],
  "30": [
    7,
    4
  ],
  "31": [
    7,
    0
  ],
  "32": [
    2,
    1
  ],
  "33": [
    14,
    4
  ],
  "34": [
    0,
    0
  ],
  "35": [
    0,
    10
  ],
  "36": [
    2,
    4
  ],
  "37": [
    0,
    3
  ],
  "38": [
    2,
    4
  ],
  "39": [
    2,
    4
  ],
  "40": [
    7,
    12
  ],
  "41": [
    2,
    12
  ],
  "42": [
    0,
    4
  ],
  "43": [
    0,
    5
  ],
  "44": [
    7,
    9
  ],
  "45": [
    7,
    0
  ],
  "46": [
    7,
    14
  ],
  "47": [
    0,
    10
  ],
  "48": [
    0,
    10
  ],
  "49": [
    0,
    5
  ],
  "50": [
    7,
    1
  ],
  "51": [
    2,
    9
  ],
  "52": [
    7,
    10
  ],
  "53": [
    2,
    0
  ],
  "54": [
    7,
    10
  ],
  "55": [
    7,
    0
  ],
  "56": [
    1,
    12
  ],
  "57": [
    1,
    4
  ],
  "58": [
    2,
    4
  ],
  "59": [
    13,
    4
  ],
  "60": [
    6,
    7
  ],
  "61": [
    15,
    0
  ],
  "62": [
    0,
    5
  ],
  "63": [
    2,
    4
  ],
  "64": [
    4,
    7
  ],
  "65": [
    7,
    14
  ],
  "66": [
    2,
    0
  ],
  "67": [
    7,
    0
  ],
  "68": [
    7,
    4
  ],
  "69": [
    7,
    0
  ],
  "70": [
    8,
    0
  ],
  "71": [
    7,
    7
  ],
  "72": [
    7,
    12
  ],
  "73": [
    8,
    0
  ],
  "74": [
    7,
    12
  ],
  "75": [
    7,
    4
  ],
  "76": [
    2,
    12
  ],
  "77": [
    8,
    0
  ],
  "78": [
    9,
    7
  ],
  "79": [
    0,
    5
  ],
  "80": [
    7,
    15
  ],
  "81": [
    7,
    0
  ],
  "82": [
    2,
    0
  ],
  "83": [
    2,
    7
  ],
  "84": [
    2,
    4
  ],
  "85": [
    7,
    4
  ],
  "86": [
    7,
    0
  ],
  "87": [
    2,
    0
  ],
  "88": [
    0,
    3
  ],
  "89": [
    7,
    12
  ],
  "90": [
    7,
    5
  ],
  "91": [
    7,
    0
  ],
  "92": [
    7,
    12
  ],
  "93": [
    7,
    10
  ],
  "94": [
    7,
    3
  ],
  "95": [
    2,
    12
  ],
  "96": [
    2,
    0
  ],
  "97": [
    7,
    4
  ],
  "98": [
    13,
    4
  ],
  "99": [
    2,
    4
  ],
  "100": [
    2,
    12
  ],
  "101": [
    12,
    0
  ],
  "102": [
    12,
    0
  ],
  "103": [
    7,
    10
  ],
  "104": [
    2,
    7
  ],
  "105": [
    2,
    10
  ],
  "106": [
    2,
    0
  ],
  "107": [
    7,
    10
  ],
  "108": [
    0,
    3
  ],
  "109": [
    7,
    10
  ],
  "110": [
    7,
    9
  ],
  "111": [
    2,
    0
  ],
  "112": [
    7,
    15
  ],
  "113": [
    2,
    7
  ],
  "114": [
    1,
    10
  ],
  "115": [
    7,
    12
  ],
  "116": [
    2,
    12
  ],
  "117": [
    2,
    7
  ],
  "118": [
    7,
    12
  ],
  "119": [
    4,
    0
  ],
  "120": [
    2,
    4
  ],
  "121": [
    2,
    12
  ],
  "122": [
    2,
    12
  ],
  "123": [
    10,
    4
  ],
  "124": [
    7,
    4
  ],
  "125": [
    2,
    0
  ],
  "126": [
    7,
    0
  ],
  "127": [
    7,
    0
  ],
  "128": [
    7,
    4
  ],
  "129": [
    7,
    10
  ],
  "130": [
    7,
    11
  ],
  "131": [
    7,
    0
  ],
  "132": [
    7,
    10
  ],
  "133": [
    7,
    4
  ],
  "134": [
    7,
    4
  ],
  "135": [
    7,
    12
  ],
  "136": [
    7,
    4
  ],
  "137": [
    7,
    4
  ],
  "138": [
    2,
    13
  ],
  "139": [
    7,
    14
  ],
  "140": [
    7,
    0
  ],
  "141": [
    7,
    3
  ],
  "142": [
    0,
    12
  ],
  "143": [
    1,
    12
  ],
  "144": [
    12,
    9
  ],
  "145": [
    2,
    4
  ],
  "146": [
    7,
    5
  ],
  "147": [
    7,
    12
  ],
  "148": [
    7,
    14
  ],
  "149": [
    7,
    12
  ],
  "150": [
    7,
    10
  ],
  "151": [
    2,
    0
  ],
  "152": [
    7,
    12
  ],
  "153": [
    7,
    0
  ],
  "154": [
    7,
    14
  ],
  "155": [
    4,
    10
  ],
  "156": [
    7,
    12
  ],
  "157": [
    0,
    10
  ],
  "158": [
    2,
    14
  ],
  "159": [
    7,
    12
  ],
  "160": [
    5,
    0
  ],
  "161": [
    4,
    10
  ],
  "162": [
    2,
    2
  ],
  "163": [
    7,
    0
  ],
  "164": [
    0,
    3
  ],
  "165": [
    7,
    0
  ],
  "166": [
    7,
    3
  ],
  "167": [
    2,
    12
  ],
  "168": [
    2,
    12
  ],
  "169": [
    7,
    7
  ],
  "170": [
    4,
    7
  ],
  "171": [
    7,
    12
  ],
  "172": [
    1,
    0
  ],
  "173": [
    7,
    11
  ],
  "174": [
    2,
    10
  ],
  "175": [
    7,
    14
  ],
  "176": [
    7,
    12
  ],
  "177": [
    0,
    7
  ],
  "178": [
    0,
    7
  ],
  "179": [
    7,
    4
  ],
  "180": [
    0,
    10
  ],
  "181": [
    7,
    0
  ],
  "182": [
    2,
    12
  ],
  "183": [
    7,
    4
  ],
  "184": [
    7,
    0
  ],
  "185": [
    7,
    7
  ],
  "186": [
    7,
    12
  ],
  "187": [
    15,
    10
  ],
  "188": [
    7,
    3
  ],
  "189": [
    0,
    7
  ],
  "190": [
    7,
    1
  ],
  "191": [
    2,
    12
  ],
  "192": [
    1,
    0
  ],
  "193": [
    7,
    7
  ],
  "194": [
    2,
    4
  ],
  "195": [
    7,
    0
  ],
  "196": [
    7,
    2
  ],
  "197": [
    7,
    10
  ],
  "198": [
    14,
    4
  ],
  "199": [
    7,
    14
  ],
  "200": [
    7,
    0
  ],
  "201": [
    7,
    4
  ],
  "202": [
    7,
    4
  ],
  "203": [
    7,
    7
  ],
  "204": [
    2,
    10
  ],
  "205": [
    7,
    0
  ],
  "206": [
    2,
    10
  ],
  "207": [
    2,
    0
  ],
  "208": [
    2,
    10
  ],
  "209": [
    2,
    12
  ],
  "210": [
    7,
    12
  ],
  "211": [
    2,
    4
  ],
  "212": [
    7,
    4
  ],
  "213": [
    10,
    12
  ],
  "214": [
    7,
    0
  ],
  "215": [
    7,
    4
  ],
  "216": [
    7,
    12
  ],
  "217": [
    7,
    14
  ],
  "218": [
    7,
    15
  ],
  "219": [
    14,
    11
  ],
  "220": [
    0,
    7
  ],
  "221": [
    7,
    14
  ],
  "222": [
    7,
    9
  ],
  "223": [
    7,
    5
  ],
  "224": [
    10,
    3
  ],
  "225": [
    7,
    12
  ],
  "226": [
    10,
    7
  ],
  "227": [
    7,
    10
  ],
  "228": [
    0,
    0
  ],
  "229": [
    7,
    11
  ],
  "230": [
    7,
    5
  ],
  "231": [
    2,
    12
  ],
  "232": [
    0,
    7
  ],
  "233": [
    7,
    4
  ],
  "234": [
    0,
    10
  ],
  "235": [
    7,
    4
  ],
  "236": [
    7,
    12
  ],
  "237": [
    7,
    12
  ],
  "238": [
    7,
    7
  ],
  "239": [
    2,
    0
  ],
  "240": [
    7,
    0
  ],
  "241": [
    7,
    14
  ],
  "242": [
    7,
    12
  ],
  "243": [
    0,
    7
  ],
  "244": [
    2,
    12
  ],
  "245": [
    0,
    7
  ],
  "246": [
    7,
    4
  ],
  "247": [
    7,
    3
  ],
  "248": [
    0,
    4
  ],
  "249": [
    7,
    14
  ],
  "250": [
    2,
    12
  ],
  "251": [
    7,
    0
  ],
  "252": [
    0,
    7
  ],
  "253": [
    2,
    12
  ],
  "254": [
    2,
    12
  ],
  "255": [
    8,
    3
  ],
  "256": [
    7,
    10
  ]
}